{
  "0": "Victini",
  "1": "Snivy",
  "2": "Servine",
  "3": "Serperior",
  "4": "Tepig",
  "5": "Pignite",
  "6": "Emboar",
  "7": "Oshawott",
  "8": "Dewott",
  "9": "Samurott",
  "10": "Patrat",
  "11": "Watchdog",
  "12": "Lillipup",
  "13": "Herdier",
  "14": "Stoutland",
  "15": "Purrloin",
  "16": "Liepard",
  "17": "Pansage",
  "18": "Simisage",
  "19": "Pansear",
  "20": "Simisear",
  "21": "Panpour",
  "22": "Simipour",
  "23": "Munna",
  "24": "Musharna",
  "25": "Pidove",
  "26": "Tranquill",
  "27": "Unfezant",
  "28": "Blitzle",
  "29": "Zebstrika",
  "30": "Roggenrola",
  "31": "Boldore",
  "32": "Gigalith",
  "33": "Woobat",
  "34": "Swoobat",
  "35": "Drilbur",
  "36": "Excadrill",
  "37": "Audino",
  "38": "Timburr",
  "39": "Gurdurr",
  "40": "Conkeldurr",
  "41": "Tympole",
  "42": "Palpitoad",
  "43": "Seismitoad",
  "44": "Throh",
  "45": "Sawk",
  "46": "Sewaddle",
  "47": "Swadloon",
  "48": "Leavanny",
  "49": "Venipede",
  "50": "Whirlipede",
  "51": "Scolipede",
  "52": "Cottonee",
  "53": "Whimsicott",
  "54": "Petilil",
  "55": "Lilligant",
  "56": "Basculin",
  "57": "Sandile",
  "58": "Krokorok",
  "59": "Krookodile",
  "60": "Darumaka",
  "61": "Darmanitan",
  "62": "Maractus",
  "63": "Dwebble",
  "64": "Crustle",
  "65": "Scraggy",
  "66": "Scrafty",
  "67": "Sigilyph",
  "68": "Yamask",
  "69": "Cofagrigus",
  "70": "Tirtouga",
  "71": "Carracosta",
  "72": "Archen",
  "73": "Archeops",
  "74": "Trubbish",
  "75": "Garbodor",
  "76": "Zorua",
  "77": "Zoroark",
  "78": "Minccino",
  "79": "Cinccino",
  "80": "Gothita",
  "81": "Gothorita",
  "82": "Gothitelle",
  "83": "Solosis",
  "84": "Duosion",
  "85": "Reuniclus",
  "86": "Ducklett",
  "87": "Swanna",
  "88": "Vanillite",
  "89": "Vanillish",
  "90": "Vanilluxe",
  "91": "Deerling",
  "92": "Sawsbuck",
  "93": "Emolga",
  "94": "Karrablast",
  "95": "Escavalier",
  "96": "Foongus",
  "97": "Amoonguss",
  "98": "Frillish",
  "99": "Jellicent",
  "100": "Alomomola",
  "101": "Joltik",
  "102": "Galvantula",
  "103": "Ferroseed",
  "104": "Ferrothorn",
  "105": "Klink",
  "106": "Klang",
  "107": "Klinklang",
  "108": "Tynamo",
  "109": "Eelektrik",
  "110": "Eelektross",
  "111": "Elgyem",
  "112": "Beheeyem",
  "113": "Litwick",
  "114": "Lampent",
  "115": "Chandelure",
  "116": "Axew",
  "117": "Fraxure",
  "118": "Haxorus",
  "119": "Cubchoo",
  "120": "Beartic",
  "121": "Cryogonal",
  "122": "Shelmet",
  "123": "Accelgor",
  "124": "Stunfisk",
  "125": "Mienfoo",
  "126": "Mienshao",
  "127": "Druddigon",
  "128": "Golett",
  "129": "Golurk",
  "130": "Pawniard",
  "131": "Bisharp",
  "132": "Bouffalant",
  "133": "Rufflet",
  "134": "Braviary",
  "135": "Vullaby",
  "136": "Mandibuzz",
  "137": "Heatmor",
  "138": "Durant",
  "139": "Deino",
  "140": "Zweilous",
  "141": "Hydreigon",
  "142": "Larvesta",
  "143": "Volcarona",
  "144": "Cobalion",
  "145": "Terrakion",
  "146": "Virizion",
  "147": "Tornadus",
  "148": "Thundurus",
  "149": "Reshiram",
  "150": "Zekrom",
  "151": "Landorus",
  "152": "Kyurem",
  "153": "Keldeo",
  "154": "Meloetta",
  "155": "Genesect"
}
